gliner_spacy/__init__.py
gliner_spacy/pipeline.py
gliner_spacy/version.py
gliner_spacy-0.0.11.dist-info/LICENSE
gliner_spacy-0.0.11.dist-info/METADATA
gliner_spacy-0.0.11.dist-info/WHEEL
gliner_spacy-0.0.11.dist-info/entry_points.txt
gliner_spacy-0.0.11.dist-info/top_level.txt
gliner_spacy-0.0.11.dist-info/RECORD
