Metadata-Version: 2.1
Name: gliner-spacy
Version: 0.0.11
Summary: A SpaCy wrapper for the GLiNER model for enhanced Named Entity Recognition capabilities
Home-page: https://github.com/theirstory/gliner-spacy
Author: William J. B. Mattingly
Classifier: Development Status :: 3 - Alpha
Classifier: Intended Audience :: Developers
Classifier: Natural Language :: English
Classifier: Programming Language :: Python :: 3
Classifier: Programming Language :: Python :: 3.7
Classifier: Programming Language :: Python :: 3.8
Classifier: Programming Language :: Python :: 3.9
Classifier: Programming Language :: Python :: 3.10
Requires-Python: >=3.7
License-File: LICENSE
Requires-Dist: spacy>=3.0.0
Requires-Dist: gliner>=0.2.0
Requires-Dist: seaborn
Requires-Dist: matplotlib
Requires-Dist: numpy
